{
  "products": [
    {
      "id": 1747467934887,
      "name": "wee",
      "image": "https://drive.google.com/uc?export=view&id=18pZVwADcmaIwf1qLfKm4ty1vyVqZ0obW",
      "price": 2222,
      "description": "wee",
      "category": "Bracelets"
    },
    {
      "id": 1747481006910,
      "name": "new",
      "price": 4444,
      "category": "Necklace",
      "description": "pop",
      "image": "htttps:/random.com"
    },
    {
      "name": "new1",
      "price": 2222,
      "category": "Necklace",
      "description": "www",
      "image": "htttps:/random.com",
      "id": 1747461652716
    },
    {
      "name": "new2",
      "price": 4444,
      "category": "Ring",
      "description": "popppp",
      "image": "htttps:/random.com",
      "id": 1747461676882
    },
    {
      "name": "new3",
      "price": 55666,
      "category": "Necklace",
      "description": "kinh",
      "image": "htttps:/random.com",
      "id": 1747461697055
    },
    {
      "id": 1747481651701,
      "name": "new 4",
      "price": 9999,
      "category": "Necklace",
      "description": "lllll",
      "image": "https://www.indiacarnews.com/wp-content/uploads/2024/10/Upcoming-New-Cars-in-India-1068x712.webp"
    },
    {
      "id": 1747481786587,
      "name": "new 8",
      "price": 9999,
      "category": "Bracelet",
      "description": "poppp",
      "image": "htttps:/random.com"
    },
    {
      "id": 1747565243671,
      "name": "new 15",
      "price": 999,
      "category": "Bracelet",
      "description": "ww",
      "image": "htttps:/random.com"
    },
    {
      "id": 1747567224,
      "name": "new 20",
      "price": 333.0,
      "category": "333",
      "description": "dlkdd\r\n",
      "image": "https://www.google.com"
    },
    {
      "id": 1747567373,
      "name": "new 21",
      "price": 0.07,
      "category": "ff",
      "description": "ff",
      "image": "https://www.google.com"
    }
  ],
  "categories": [],
  "offers": [],
  "occasions": [],
  "updated_by": "admin",
  "updated_at": "2025-05-18T16:57:13.001374"
}